{"domain": "api1.com", "status": "exception", "available": false}
{"domain": "api2.com", "status": "exception", "available": false}
{"domain": "api3.com", "status": "exception", "available": false}
{"domain": "default-api-url.com", "status": "exception", "available": true}
{"domain": "ical-validator.info", "status": "exception", "available": true}
{"domain": "watir.com", "status": "exception", "available": false}
{"domain": "codepad.org", "status": "exception", "available": false}
{"domain": "my-jenkins-instance.com", "status": "exception", "available": true}
{"domain": "www.php2exe.net", "status": "exception", "available": true}
{"domain": "www.pagodabox.com", "status": "exception", "available": false}
{"domain": "phalanger.cz", "status": "exception", "available": true}
{"domain": "www.newdomain.com", "status": "exception", "available": false}
{"domain": "polygit.org", "status": "exception", "available": false}
{"domain": "keyjerk.com", "status": "exception", "available": true}
{"domain": "regex101.com", "status": "exception", "available": false}
{"domain": "picsum.photos", "status": "exception", "available": false}
{"domain": "www.catalystframework.org", "status": "exception", "available": false}
{"domain": "www.phploader.com", "status": "exception", "available": true}
{"domain": "www.drpython.org", "status": "exception", "available": true}
{"domain": "symfony.com", "status": "exception", "available": false}
{"domain": "www.mozilla.org", "status": "exception", "available": false}
{"domain": "www.webfaction.com", "status": "exception", "available": false}
{"domain": "my-function-url.com", "status": "exception", "available": true}
{"domain": "my-run-url.com", "status": "exception", "available": true}
{"domain": "api.execute", "status": "exception", "available": true}
{"domain": "melpa.org", "status": "exception", "available": false}
{"domain": "signal-desktop-api.com", "status": "exception", "available": true}
{"domain": "legacy-website.com", "status": "exception", "available": true}
{"domain": "www.elastic.co", "status": "exception", "available": false}
{"domain": "openphpsdk.com", "status": "exception", "available": true}
{"domain": "ffmpeg-php.com", "status": "exception", "available": true}
{"domain": "fontjs.org", "status": "exception", "available": true}
{"domain": "alternative-url.com", "status": "exception", "available": false}
{"domain": "www.graphql-security.com", "status": "exception", "available": true}
{"domain": "www.fontinst.org", "status": "exception", "available": true}
{"domain": "prawnrb.com", "status": "exception", "available": true}
{"domain": "docopt.org", "status": "exception", "available": false}
{"domain": "imagecoverdetection.com", "status": "exception", "available": true}
{"domain": "coverdetection.com", "status": "exception", "available": true}
{"domain": "xmlsoft.org", "status": "exception", "available": false}
{"domain": "polyfill.io", "status": "exception", "available": false}
{"domain": "github-enterprise.com", "status": "exception", "available": false}
{"domain": "my-private-registry.com", "status": "exception", "available": true}
{"domain": "graphql.org", "status": "exception", "available": false}
{"domain": "shoesrb.com", "status": "exception", "available": false}
{"domain": "portablepython.org", "status": "exception", "available": true}
{"domain": "liteide.org", "status": "exception", "available": false}
{"domain": "corcel.com", "status": "exception", "available": true}
{"domain": "json-schema.org", "status": "exception", "available": false}
{"domain": "php3d.org", "status": "exception", "available": true}
{"domain": "www.pythonfx.org", "status": "exception", "available": true}
{"domain": "almsaeedstudio.com", "status": "exception", "available": false}
{"domain": "www.amazon.com", "status": 500, "available": false}
{"domain": "php-gettext.com", "status": "exception", "available": true}
{"domain": "yourwebsite.com", "status": "exception", "available": false}
{"domain": "badwords.net", "status": "exception", "available": false}
{"domain": "www.sentiment140.com", "status": "exception", "available": false}
{"domain": "www.myopenid.com", "status": "exception", "available": false}
{"domain": "www.gzip-online.com", "status": "exception", "available": false}
{"domain": "brotli.com", "status": "exception", "available": false}
{"domain": "vwo-static.com", "status": "exception", "available": true}
{"domain": "private-module-1.com", "status": "exception", "available": true}
{"domain": "private-module-2.com", "status": "exception", "available": true}
{"domain": "public-module-1.com", "status": "exception", "available": true}
{"domain": "public-module-2.com", "status": "exception", "available": true}
{"domain": "another.com", "status": "exception", "available": true}
{"domain": "theantlrguy.com", "status": "exception", "available": true}
{"domain": "order-processing-service.com", "status": "exception", "available": true}
{"domain": "invalid-url.com", "status": "exception", "available": true}
{"domain": "anotherdomain.com", "status": "exception", "available": true}
{"domain": "airport-codes.io", "status": "exception", "available": true}
{"domain": "trello.com", "status": 401, "available": false}
{"domain": "second-api.com", "status": "exception", "available": true}
{"domain": "www.sinatrarb.com", "status": "exception", "available": false}
{"domain": "www.openflashchart.net", "status": "exception", "available": true}
{"domain": "openflashchart.com", "status": "exception", "available": true}
{"domain": "openflashcharts.com", "status": "exception", "available": true}
{"domain": "rubyx-repo.org", "status": "exception", "available": true}
{"domain": "mywebsite.com", "status": 436, "available": false}
{"domain": "sonarcloud.io", "status": 400, "available": false}
{"domain": "new-0.com", "status": "exception", "available": false}
{"domain": "cloudmac.io", "status": "exception", "available": true}
{"domain": "new-host.com", "status": "exception", "available": true}
{"domain": "newdomain.com", "status": "exception", "available": false}
{"domain": "www.cmegroup.com", "status": "exception", "available": false}
{"domain": "slowwebsite.com", "status": "exception", "available": false}
{"domain": "csgocrash.com", "status": "exception", "available": false}
{"domain": "www.costco.com", "status": "exception", "available": false}
{"domain": "www.walmart.com", "status": "exception", "available": false}
{"domain": "www.htmlparser.org", "status": "exception", "available": false}
{"domain": "trusted-source.com", "status": "exception", "available": false}
{"domain": "3rd-party-site.com", "status": "exception", "available": true}
{"domain": "my-go-server.com", "status": "exception", "available": true}
{"domain": "support.google", "status": "exception", "available": false}
{"domain": "eric-ide.org", "status": "exception", "available": true}
{"domain": "parsecdn.org", "status": "exception", "available": true}
